mcspy/__init__.py
mcspy/mcspy.py
mcspy-1.3.1.dist-info/METADATA
mcspy-1.3.1.dist-info/WHEEL
mcspy-1.3.1.dist-info/top_level.txt
mcspy-1.3.1.dist-info/RECORD
