Metadata-Version: 2.1
Name: mcspy
Version: 1.3.1
Summary: A Python Library for Mobile Crowdsensing Problems
Author: Han Yaohui
Author-email: han0129@csu.edc.cn
License: MIT
